oktagon_python/__init__.py
oktagon_python/_version.py
oktagon_python/authorisation.py
oktagon_python-0.0.18.dist-info/LICENCE
oktagon_python-0.0.18.dist-info/METADATA
oktagon_python-0.0.18.dist-info/WHEEL
oktagon_python-0.0.18.dist-info/top_level.txt
oktagon_python-0.0.18.dist-info/RECORD
