Metadata-Version: 2.1
Name: oktagon-python
Version: 0.0.18
Summary: Python utility package for verifying & decoding OKTA tokens
Home-page: https://github.com/madedotcom/oktagon-python
Author: Made.com Tech Team
Author-email: tech@made.com
License: MIT
Keywords: okta,python,authorisation
Classifier: Development Status :: 5 - Production/Stable
Classifier: Intended Audience :: Developers
Classifier: Topic :: Software Development :: Libraries
Classifier: Topic :: Software Development :: Libraries :: Python Modules
Classifier: License :: OSI Approved :: MIT License
License-File: LICENCE
Requires-Dist: okta-jwt-verifier
Requires-Dist: starlette
Provides-Extra: build
Requires-Dist: build ; extra == 'build'
Provides-Extra: coverage
Requires-Dist: coverage ; extra == 'coverage'
Provides-Extra: tests
Requires-Dist: coverage ; extra == 'tests'
Requires-Dist: pytest ; extra == 'tests'
Requires-Dist: pytest-asyncio ; extra == 'tests'
Requires-Dist: pytest-cov ; extra == 'tests'
Requires-Dist: pylint ; extra == 'tests'
Requires-Dist: black ; extra == 'tests'
Requires-Dist: isort ; extra == 'tests'
